ark/__init__.py
ark/settings.py
ark/analysis/__init__.py
ark/analysis/cell_neighborhood_stats.py
ark/analysis/dimensionality_reduction.py
ark/analysis/neighborhood_analysis.py
ark/analysis/spatial_analysis_utils.py
ark/analysis/visualize.py
ark/phenotyping/__init__.py
ark/phenotyping/cell_cluster_utils.py
ark/phenotyping/cell_meta_clustering.py
ark/phenotyping/cell_som_clustering.py
ark/phenotyping/cluster_helpers.py
ark/phenotyping/pixel_cluster_utils.py
ark/phenotyping/pixel_meta_clustering.py
ark/phenotyping/pixel_som_clustering.py
ark/phenotyping/pixie_preprocessing.py
ark/phenotyping/post_cluster_utils.py
ark/phenotyping/weighted_channel_comp.py
ark/segmentation/__init__.py
ark/segmentation/fiber_segmentation.py
ark/segmentation/marker_quantification.py
ark/segmentation/regionprops_extraction.py
ark/segmentation/segmentation_utils.py
ark/segmentation/signal_extraction.py
ark/segmentation/ez_seg/__init__.py
ark/segmentation/ez_seg/composites.py
ark/segmentation/ez_seg/ez_object_segmentation.py
ark/segmentation/ez_seg/ez_seg_display.py
ark/segmentation/ez_seg/ez_seg_utils.py
ark/segmentation/ez_seg/merge_masks.py
ark/spLDA/__init__.py
ark/spLDA/processing.py
ark/utils/__init__.py
ark/utils/data_utils.py
ark/utils/deepcell_service_utils.py
ark/utils/example_dataset.py
ark/utils/masking_utils.py
ark/utils/plot_utils.py
ark/utils/spatial_lda_utils.py
ark/utils/metacluster_remap_gui/__init__.py
ark/utils/metacluster_remap_gui/colormap_helper.py
ark/utils/metacluster_remap_gui/file_reader.py
ark/utils/metacluster_remap_gui/metaclusterdata.py
ark/utils/metacluster_remap_gui/metaclustergui.py
ark/utils/metacluster_remap_gui/throttle.py
ark/utils/metacluster_remap_gui/zscore_norm.py
ark_analysis-0.7.2.dist-info/METADATA
ark_analysis-0.7.2.dist-info/WHEEL
ark_analysis-0.7.2.dist-info/licenses/LICENSE
ark_analysis-0.7.2.dist-info/RECORD
