Metadata-Version: 2.3
Name: ark-analysis
Version: 0.7.2
Summary: Toolbox for analysis on segmented images from MIBI.
Project-URL: Documentation, https://ark-analysis.readthedocs.io/en/latest/
Project-URL: Source, https://github.com/angelolab/ark-analysis
Project-URL: Home-page, https://github.com/angelolab/ark-analysis
Author-email: Angelo Lab <theangelolab@gmail.com>
Maintainer-email: Noah Frey Greenwald <nfgreen@stanford.edu>, Alex Kong <alkong@stanford.edu>, Cameron Laura Sowers <csowers@stanford.edu>, Sricharan Reddy Varra <srivarra@stanford.edu>
License: The MIT License (MIT)
License-File: LICENSE
Classifier: Development Status :: 4 - Beta
Classifier: License :: OSI Approved :: Apache Software License
Classifier: Programming Language :: Python :: 3
Classifier: Programming Language :: Python :: 3.9
Classifier: Programming Language :: Python :: 3.10
Classifier: Programming Language :: Python :: 3.11
Classifier: Topic :: Scientific/Engineering :: Bio-Informatics
Requires-Python: >=3.9
Requires-Dist: alpineer==0.1.12
Requires-Dist: anndata
Requires-Dist: ark-analysis[colors]
Requires-Dist: datasets<3.0,>=2.6
Requires-Dist: dill<0.4,>=0.3.5
Requires-Dist: feather-format<1,>=0.4.1
Requires-Dist: graphviz
Requires-Dist: importlib-metadata>=5.0
Requires-Dist: ipympl<1.0.0,>=0.9.2
Requires-Dist: ipython<9,>=8.4
Requires-Dist: jupyterlab<4,>=3.4.3
Requires-Dist: matplotlib<4,>=3.7
Requires-Dist: multiprocess>=0.70.13
Requires-Dist: natsort<9,>=8
Requires-Dist: numpy<1.24,>=1.20
Requires-Dist: palettable<4,>=3.3.0
Requires-Dist: pandas>=2
Requires-Dist: pillow<10,>=9
Requires-Dist: pyflowsom>=0.1.16
Requires-Dist: python-dateutil>=2.9.0
Requires-Dist: requests<3,>=2.20
Requires-Dist: scikit-image<0.19.3
Requires-Dist: scikit-learn<2,>=1.1
Requires-Dist: scipy<2,>=1.7
Requires-Dist: seaborn<1,>=0.12
Requires-Dist: spatial-lda<1,>=0.1.3
Requires-Dist: statsmodels<1,>=0.13.2
Requires-Dist: tifffile>=2022
Requires-Dist: tqdm<5,>=4
Requires-Dist: umap-learn<1.0,>=0.5
Requires-Dist: xarray>=2022
Requires-Dist: xmltodict<1,>=0.13.0
Requires-Dist: zarr
Requires-Dist: zstandard<1,>=0.19.0
Provides-Extra: colors
Requires-Dist: cmasher; extra == 'colors'
Requires-Dist: cmocean; extra == 'colors'
Requires-Dist: colorcet; extra == 'colors'
Requires-Dist: palettable; extra == 'colors'
Requires-Dist: scienceplots; extra == 'colors'
Provides-Extra: dev
Requires-Dist: attrs; extra == 'dev'
Requires-Dist: coveralls[toml]; extra == 'dev'
Requires-Dist: pytest; extra == 'dev'
Requires-Dist: pytest-asyncio; extra == 'dev'
Requires-Dist: pytest-cases; extra == 'dev'
Requires-Dist: pytest-cov; extra == 'dev'
Requires-Dist: pytest-mock; extra == 'dev'
Requires-Dist: pytest-pycodestyle; extra == 'dev'
Requires-Dist: pytest-randomly; extra == 'dev'
Requires-Dist: testbook; extra == 'dev'
Requires-Dist: twine; extra == 'dev'
Provides-Extra: lab-ext
Requires-Dist: jupyterlab-execute-time; extra == 'lab-ext'
Requires-Dist: jupyterlab-git; extra == 'lab-ext'
Requires-Dist: jupyterlab-lsp; extra == 'lab-ext'
Requires-Dist: jupyterlab-skip-traceback; extra == 'lab-ext'
Requires-Dist: lckr-jupyterlab-variableinspector; extra == 'lab-ext'
Requires-Dist: python-lsp-server[all]; extra == 'lab-ext'
Provides-Extra: test
Requires-Dist: attrs; extra == 'test'
Requires-Dist: coveralls[toml]; extra == 'test'
Requires-Dist: pytest; extra == 'test'
Requires-Dist: pytest-asyncio; extra == 'test'
Requires-Dist: pytest-cases; extra == 'test'
Requires-Dist: pytest-cov; extra == 'test'
Requires-Dist: pytest-mock; extra == 'test'
Requires-Dist: pytest-pycodestyle; extra == 'test'
Requires-Dist: pytest-randomly; extra == 'test'
Requires-Dist: testbook; extra == 'test'
